
{
  "header": {
    "reportVersion": 1,
    "event": "Allocation failed - JavaScript heap out of memory",
    "trigger": "FatalError",
    "filename": "report.20200304.222948.8972.0.001.json",
    "dumpEventTime": "2020-03-04T22:29:48Z",
    "dumpEventTimeStamp": "1583371788517",
    "processId": 8972,
    "cwd": "C:\\dev\\angular\\frases",
    "commandLine": [
      "C:\\Program Files\\nodejs\\node.exe",
      "C:\\dev\\angular\\frases\\node_modules\\jest-worker\\build\\workers\\processChild.js"
    ],
    "nodejsVersion": "v12.14.1",
    "wordSize": 64,
    "arch": "x64",
    "platform": "win32",
    "componentVersions": {
      "node": "12.14.1",
      "v8": "7.7.299.13-node.16",
      "uv": "1.33.1",
      "zlib": "1.2.11",
      "brotli": "1.0.7",
      "ares": "1.15.0",
      "modules": "72",
      "nghttp2": "1.40.0",
      "napi": "5",
      "llhttp": "2.0.1",
      "http_parser": "2.8.0",
      "openssl": "1.1.1d",
      "cldr": "35.1",
      "icu": "64.2",
      "tz": "2019c",
      "unicode": "12.1"
    },
    "release": {
      "name": "node",
      "lts": "Erbium",
      "headersUrl": "https://nodejs.org/download/release/v12.14.1/node-v12.14.1-headers.tar.gz",
      "sourceUrl": "https://nodejs.org/download/release/v12.14.1/node-v12.14.1.tar.gz",
      "libUrl": "https://nodejs.org/download/release/v12.14.1/win-x64/node.lib"
    },
    "osName": "Windows_NT",
    "osRelease": "10.0.18363",
    "osVersion": "Windows 10 Pro",
    "osMachine": "x86_64",
    "cpus": [
      {
        "model": "Intel(R) Core(TM) i5 CPU       M 560  @ 2.67GHz",
        "speed": 2660,
        "user": 4398796,
        "nice": 0,
        "sys": 1409250,
        "idle": 34697765,
        "irq": 152843
      },
      {
        "model": "Intel(R) Core(TM) i5 CPU       M 560  @ 2.67GHz",
        "speed": 2660,
        "user": 3552812,
        "nice": 0,
        "sys": 1084109,
        "idle": 35868656,
        "irq": 20953
      },
      {
        "model": "Intel(R) Core(TM) i5 CPU       M 560  @ 2.67GHz",
        "speed": 2660,
        "user": 3848234,
        "nice": 0,
        "sys": 1195906,
        "idle": 35461437,
        "irq": 23890
      },
      {
        "model": "Intel(R) Core(TM) i5 CPU       M 560  @ 2.67GHz",
        "speed": 2660,
        "user": 5005218,
        "nice": 0,
        "sys": 1166562,
        "idle": 34333796,
        "irq": 18625
      }
    ],
    "networkInterfaces": [
      {
        "name": "Ethernet",
        "internal": false,
        "mac": "f0:4d:a2:b0:b3:3c",
        "address": "fe80::ed51:ba93:1d49:b74a",
        "netmask": "ffff:ffff:ffff:ffff::",
        "family": "IPv6",
        "scopeid": 3
      },
      {
        "name": "Ethernet",
        "internal": false,
        "mac": "f0:4d:a2:b0:b3:3c",
        "address": "192.168.1.131",
        "netmask": "255.255.255.0",
        "family": "IPv4"
      },
      {
        "name": "Loopback Pseudo-Interface 1",
        "internal": true,
        "mac": "00:00:00:00:00:00",
        "address": "::1",
        "netmask": "ffff:ffff:ffff:ffff:ffff:ffff:ffff:ffff",
        "family": "IPv6",
        "scopeid": 0
      },
      {
        "name": "Loopback Pseudo-Interface 1",
        "internal": true,
        "mac": "00:00:00:00:00:00",
        "address": "127.0.0.1",
        "netmask": "255.0.0.0",
        "family": "IPv4"
      }
    ],
    "host": "DESKTOP-9R4R9AP"
  },
  "javascriptStack": {
    "message": "No stack.",
    "stack": [
      "Unavailable."
    ]
  },
  "nativeStack": [
    {
      "pc": "0x00007ff6a2fb1759",
      "symbol": "std::basic_ostream<char,std::char_traits<char> >::operator<<+10873"
    },
    {
      "pc": "0x00007ff6a2fb5b7c",
      "symbol": "std::basic_ostream<char,std::char_traits<char> >::operator<<+28316"
    },
    {
      "pc": "0x00007ff6a2fb4b38",
      "symbol": "std::basic_ostream<char,std::char_traits<char> >::operator<<+24152"
    },
    {
      "pc": "0x00007ff6a30a433b",
      "symbol": "v8::base::CPU::has_sse+37723"
    },
    {
      "pc": "0x00007ff6a38a8c5e",
      "symbol": "v8::Isolate::ReportExternalAllocationLimitReached+94"
    },
    {
      "pc": "0x00007ff6a3890ca1",
      "symbol": "v8::SharedArrayBuffer::Externalize+833"
    },
    {
      "pc": "0x00007ff6a375e56c",
      "symbol": "v8::internal::Heap::EphemeronKeyWriteBarrierFromCode+1436"
    },
    {
      "pc": "0x00007ff6a3769910",
      "symbol": "v8::internal::Heap::ProtectUnprotectedMemoryChunks+1312"
    },
    {
      "pc": "0x00007ff6a3766444",
      "symbol": "v8::internal::Heap::PageFlagsAreConsistent+3204"
    },
    {
      "pc": "0x00007ff6a375bcd3",
      "symbol": "v8::internal::Heap::CollectGarbage+1283"
    },
    {
      "pc": "0x00007ff6a375a4a4",
      "symbol": "v8::internal::Heap::AddRetainedMap+2356"
    },
    {
      "pc": "0x00007ff6a377b775",
      "symbol": "v8::internal::Factory::NewFillerObject+53"
    },
    {
      "pc": "0x00007ff6a34e7a49",
      "symbol": "v8::internal::interpreter::JumpTableTargetOffsets::iterator::operator=+4057"
    },
    {
      "pc": "0x00007ff6a3cd463d",
      "symbol": "v8::internal::SetupIsolateDelegate::SetupHeap+567949"
    },
    {
      "pc": "0x00007ff6a3c8770e",
      "symbol": "v8::internal::SetupIsolateDelegate::SetupHeap+252766"
    },
    {
      "pc": "0x000002515e77b0f6",
      "symbol": ""
    }
  ],
  "javascriptHeap": {
    "totalMemory": 2045353984,
    "totalCommittedMemory": 2045353984,
    "usedMemory": 2032976888,
    "availableMemory": 48794568,
    "memoryLimit": 2091909120,
    "heapSpaces": {
      "read_only_space": {
        "memorySize": 262144,
        "committedMemory": 262144,
        "capacity": 261872,
        "used": 32296,
        "available": 229576
      },
      "new_space": {
        "memorySize": 2097152,
        "committedMemory": 2097152,
        "capacity": 1047488,
        "used": 190288,
        "available": 857200
      },
      "old_space": {
        "memorySize": 1969598464,
        "committedMemory": 1969598464,
        "capacity": 1960259784,
        "used": 1960154616,
        "available": 105168
      },
      "code_space": {
        "memorySize": 1474560,
        "committedMemory": 1474560,
        "capacity": 1208928,
        "used": 1208928,
        "available": 0
      },
      "map_space": {
        "memorySize": 1314816,
        "committedMemory": 1314816,
        "capacity": 920240,
        "used": 920240,
        "available": 0
      },
      "large_object_space": {
        "memorySize": 70557696,
        "committedMemory": 70557696,
        "capacity": 70466872,
        "used": 70466872,
        "available": 0
      },
      "code_large_object_space": {
        "memorySize": 49152,
        "committedMemory": 49152,
        "capacity": 3648,
        "used": 3648,
        "available": 0
      },
      "new_large_object_space": {
        "memorySize": 0,
        "committedMemory": 0,
        "capacity": 1047488,
        "used": 0,
        "available": 1047488
      }
    }
  },
  "resourceUsage": {
    "userCpuSeconds": 265.187,
    "kernelCpuSeconds": 7.968,
    "cpuConsumptionPercent": 197.938,
    "maxRss": 2093162496,
    "pageFaults": {
      "IORequired": 1292896,
      "IONotRequired": 0
    },
    "fsActivity": {
      "reads": 892,
      "writes": 109
    }
  },
  "libuv": [
  ],
  "environmentVariables": {
    "ALLUSERSPROFILE": "C:\\ProgramData",
    "APPDATA": "C:\\Users\\Leandro\\AppData\\Roaming",
    "APPLICATION_INSIGHTS_NO_DIAGNOSTIC_CHANNEL": "true",
    "BROWSERSLIST_IGNORE_OLD_DATA": "1",
    "COLORTERM": "truecolor",
    "CommonProgramFiles": "C:\\Program Files\\Common Files",
    "CommonProgramFiles(x86)": "C:\\Program Files (x86)\\Common Files",
    "CommonProgramW6432": "C:\\Program Files\\Common Files",
    "COMPUTERNAME": "DESKTOP-9R4R9AP",
    "ComSpec": "C:\\WINDOWS\\system32\\cmd.exe",
    "DriverData": "C:\\Windows\\System32\\Drivers\\DriverData",
    "FORCE_COLOR": "1",
    "FPS_BROWSER_APP_PROFILE_STRING": "Internet Explorer",
    "FPS_BROWSER_USER_PROFILE_STRING": "Default",
    "HOMEDRIVE": "C:",
    "HOMEPATH": "\\Users\\Leandro",
    "JEST_WORKER_ID": "3",
    "LANG": "pt_BR.UTF-8",
    "LOCALAPPDATA": "C:\\Users\\Leandro\\AppData\\Local",
    "LOGONSERVER": "\\\\DESKTOP-9R4R9AP",
    "NUMBER_OF_PROCESSORS": "4",
    "OneDrive": "C:\\Users\\Leandro\\OneDrive",
    "OS": "Windows_NT",
    "Path": "C:\\WINDOWS\\system32;C:\\WINDOWS;C:\\WINDOWS\\System32\\Wbem;C:\\WINDOWS\\System32\\WindowsPowerShell\\v1.0\\;C:\\WINDOWS\\System32\\OpenSSH\\;C:\\Program Files\\Git\\cmd;C:\\Program Files\\nodejs\\;C:\\Program Files\\PowerShell\\6\\;C:\\Users\\Leandro\\AppData\\Local\\Microsoft\\WindowsApps;;C:\\Users\\Leandro\\AppData\\Local\\Programs\\Microsoft VS Code\\bin;C:\\Users\\Leandro\\AppData\\Roaming\\npm",
    "PATHEXT": ".COM;.EXE;.BAT;.CMD;.VBS;.VBE;.JS;.JSE;.WSF;.WSH;.MSC",
    "PROCESSOR_ARCHITECTURE": "AMD64",
    "PROCESSOR_IDENTIFIER": "Intel64 Family 6 Model 37 Stepping 5, GenuineIntel",
    "PROCESSOR_LEVEL": "6",
    "PROCESSOR_REVISION": "2505",
    "ProgramData": "C:\\ProgramData",
    "ProgramFiles": "C:\\Program Files",
    "ProgramFiles(x86)": "C:\\Program Files (x86)",
    "ProgramW6432": "C:\\Program Files",
    "PROMPT": "$P$G",
    "PSModulePath": "C:\\Users\\Leandro\\Documents\\PowerShell\\Modules;C:\\Program Files\\PowerShell\\Modules;c:\\program files\\powershell\\6\\Modules;C:\\WINDOWS\\system32\\WindowsPowerShell\\v1.0\\Modules",
    "PUBLIC": "C:\\Users\\Public",
    "SESSIONNAME": "Console",
    "SystemDrive": "C:",
    "SystemRoot": "C:\\WINDOWS",
    "TEMP": "C:\\Users\\Leandro\\AppData\\Local\\Temp",
    "TERM_PROGRAM": "vscode",
    "TERM_PROGRAM_VERSION": "1.42.1",
    "TMP": "C:\\Users\\Leandro\\AppData\\Local\\Temp",
    "USERDOMAIN": "DESKTOP-9R4R9AP",
    "USERDOMAIN_ROAMINGPROFILE": "DESKTOP-9R4R9AP",
    "USERNAME": "Leandro",
    "USERPROFILE": "C:\\Users\\Leandro",
    "WEBPACK_DEV_SERVER": "true",
    "windir": "C:\\WINDOWS"
  },
  "sharedObjects": [
    "C:\\Program Files\\nodejs\\node.exe",
    "C:\\WINDOWS\\SYSTEM32\\ntdll.dll",
    "C:\\Program Files\\AVAST Software\\Avast\\aswhook.dll",
    "C:\\WINDOWS\\System32\\KERNEL32.DLL",
    "C:\\WINDOWS\\System32\\KERNELBASE.dll",
    "C:\\WINDOWS\\System32\\WS2_32.dll",
    "C:\\WINDOWS\\System32\\RPCRT4.dll",
    "C:\\WINDOWS\\System32\\ADVAPI32.dll",
    "C:\\WINDOWS\\System32\\msvcrt.dll",
    "C:\\WINDOWS\\System32\\sechost.dll",
    "C:\\WINDOWS\\System32\\USER32.dll",
    "C:\\WINDOWS\\System32\\win32u.dll",
    "C:\\WINDOWS\\System32\\GDI32.dll",
    "C:\\WINDOWS\\System32\\gdi32full.dll",
    "C:\\WINDOWS\\System32\\msvcp_win.dll",
    "C:\\WINDOWS\\System32\\ucrtbase.dll",
    "C:\\WINDOWS\\System32\\PSAPI.DLL",
    "C:\\WINDOWS\\System32\\CRYPT32.dll",
    "C:\\WINDOWS\\System32\\MSASN1.dll",
    "C:\\WINDOWS\\System32\\bcrypt.dll",
    "C:\\WINDOWS\\SYSTEM32\\dbghelp.dll",
    "C:\\WINDOWS\\SYSTEM32\\IPHLPAPI.DLL",
    "C:\\WINDOWS\\SYSTEM32\\USERENV.dll",
    "C:\\WINDOWS\\System32\\profapi.dll",
    "C:\\WINDOWS\\SYSTEM32\\WINMM.dll",
    "C:\\WINDOWS\\SYSTEM32\\WINMMBASE.dll",
    "C:\\WINDOWS\\System32\\cfgmgr32.dll",
    "C:\\WINDOWS\\System32\\bcryptPrimitives.dll",
    "C:\\WINDOWS\\System32\\IMM32.DLL",
    "C:\\WINDOWS\\System32\\powrprof.dll",
    "C:\\WINDOWS\\System32\\UMPDC.dll",
    "C:\\WINDOWS\\SYSTEM32\\CRYPTBASE.DLL",
    "C:\\WINDOWS\\system32\\uxtheme.dll",
    "C:\\WINDOWS\\System32\\combase.dll",
    "C:\\WINDOWS\\system32\\mswsock.dll",
    "C:\\WINDOWS\\System32\\kernel.appcore.dll",
    "C:\\WINDOWS\\System32\\NSI.dll",
    "C:\\WINDOWS\\SYSTEM32\\dhcpcsvc6.DLL",
    "C:\\WINDOWS\\SYSTEM32\\dhcpcsvc.DLL",
    "C:\\WINDOWS\\SYSTEM32\\DNSAPI.dll",
    "C:\\WINDOWS\\system32\\napinsp.dll",
    "C:\\WINDOWS\\system32\\pnrpnsp.dll",
    "C:\\WINDOWS\\System32\\winrnr.dll",
    "C:\\WINDOWS\\system32\\NLAapi.dll",
    "C:\\WINDOWS\\system32\\wshbth.dll"
  ]
}